{
        "Noutbuk": {
            "sub_types": {
                "Коммерческий": 4,
                "Общее назначение": 2,
                "Форм-фактор": 1,
                "Процессор": 2,
                "Графика": 3,
                "": 1
            },
            "classes": {
                "Премиальный": 1,
                "Уьтрабук": 2,
                "Простейший, начального уровня": 3,
                "Для коммуникаций и просмотра": 1,
                "Для обычной работы и учебы": 3,
                "Универсальный домашний": 4,
                "Игровой": 5,
                "Для творчества или разработки": 6,
                "Профессиональная рабочая станция": 7,

                "Корпоративный": 3,
                "Бизнес средний": 2,
                "Для массовых рабочих мест": 1,
                "Младшего класса": 1,
                "Стандартный мобильный": 2,
                "Для продвинутых ноутбуков": 3,
                "Встроенная": 1,
                "Легкая внешняя": 2,
                "Игровая или профессиональная": 3,
                "Трансформер с поворотным экраном": 6,
                "Мини до 12\"": 1,
                "Ультракомпактный 13\"": 2,
                "Компактный 14\"": 3,
                "Стандартный размер 15\"": 4,
                "Большой экран 16\" и более": 5

            }
        },
        "Monitor": {
            "sub_types": {
                "Экран монитора": 2
            },
            "classes": {
                "Начального уровня": 1,
                "Офисный": 4,
                "Игровой": 3,
                "Профессиональный": 5,
                "Премиальный": 6,
                "Универсальный, для учебы и работы": 2,
                "IPS": 4,
                "4K": 2,
                "2K": 1,
                "Вогнутый": 3
            }
        },
        "Printer-mfu":
        {
            "sub_types": {
                "Общее назначение": 2,
                "Фото": 2,
                "Коммерческий": 3,
                "Тип аппарата": 2,
                "": 1,
                "Цвет": 3,
                "Технология печати": 4,
                "Коммуникации": 5

            },
            "classes": {
                "Для малого и домашнего офиса": 1,
                "Для офиса с умеренной печатью": 2,
                "Для офиса с интенсивной печатью": 3
            }
        },
        "Ups":
        {
            "sub_types": {
                "Домашний": 1,
                "Коммерческий": 2,
                "Подключение": 1,
                "Топология включения в линию": 2,
                "Форм-фактор": 3
            },
           "classes": {

           }
        }
    }